endlessh/__init__.py
endlessh/http.py
endlessh/ssh.py
endlessh-0.0.11.dist-info/LICENSE
endlessh-0.0.11.dist-info/METADATA
endlessh-0.0.11.dist-info/WHEEL
endlessh-0.0.11.dist-info/entry_points.txt
endlessh-0.0.11.dist-info/top_level.txt
endlessh-0.0.11.dist-info/RECORD
