Metadata-Version: 2.1
Name: endlessh
Version: 0.0.11
Summary: SSH honeypot implemented with Python
Home-page: https://github.com/GaoangLiu/pyendlessh
Author: slipper
Author-email: r2fscg@gmail.com
License: UNKNOWN
Platform: UNKNOWN
Classifier: Programming Language :: Python :: 3
Classifier: License :: OSI Approved :: MIT License
Classifier: Operating System :: OS Independent
License-File: LICENSE
Requires-Dist: argparse
Requires-Dist: codefast
Requires-Dist: colorama
Requires-Dist: paramiko
